{
  "schema_version": 1,
  "product_id": "ao-62162",
  "category": "fridge",
  "brand": "Beko",
  "model": "BSB641X",
  "source_url": "https://www.appliancesonline.com.au/ak/8/4/6/0/846020fc52b75467bdc517c7a079ca79a5077e2d_Beko_BSB641X_641L_Side_by_Side_Fridge_Specifications_Sheet_2.pdf",
  "verified_at": "2026-05-09",
  "extracted": {
    "brand": "Beko",
    "sku": "BSB641X",
    "category": "FRIDGE",
    "dimensions": {
      "height_mm": 1790,
      "width_mm": 910,
      "depth_mm": 720,
      "door_open_90_depth_mm": null
    },
    "clearance_requirements": {
      "top_mm": 0,
      "left_mm": 0,
      "right_mm": 0,
      "rear_mm": 0
    },
    "flags": {
      "requires_plumbing": false,
      "ventilation_required": true,
      "reversible_door": null
    },
    "metadata": {
      "source_pdf_url": "https://www.appliancesonline.com.au/ak/8/4/6/0/846020fc52b75467bdc517c7a079ca79a5077e2d_Beko_BSB641X_641L_Side_by_Side_Fridge_Specifications_Sheet_2.pdf",
      "extraction_date": "2026-05-09T09:02:49.924Z",
      "confidence_score": 0.9
    }
  }
}
