{
  "schema_version": 1,
  "product_id": "ao-78952",
  "category": "dishwasher",
  "brand": "Smeg",
  "model": "DWA6315W2",
  "source_url": "https://www.appliancesonline.com.au/ak/4/6/8/4/4684351007109dcab141ed5d779db53e45399936_DWA6315W2_Smeg_Specifications_Sheet.pdf",
  "verified_at": "2026-05-09",
  "extracted": {
    "brand": "Smeg",
    "sku": "DWA6315W2",
    "category": "DISHWASHER",
    "dimensions": {
      "height_mm": 850,
      "width_mm": 598,
      "depth_mm": 600,
      "door_open_90_depth_mm": null
    },
    "clearance_requirements": {
      "top_mm": 0,
      "left_mm": 0,
      "right_mm": 0,
      "rear_mm": 0
    },
    "flags": {
      "requires_plumbing": false,
      "ventilation_required": true,
      "reversible_door": null
    },
    "metadata": {
      "source_pdf_url": "https://www.appliancesonline.com.au/ak/4/6/8/4/4684351007109dcab141ed5d779db53e45399936_DWA6315W2_Smeg_Specifications_Sheet.pdf",
      "extraction_date": "2026-05-09T08:50:46.231Z",
      "confidence_score": 0.9
    }
  }
}
