{
  "schema_version": 1,
  "product_id": "ao-52318",
  "category": "fridge",
  "brand": "LG",
  "model": "GB-450UPLX",
  "source_url": "https://www.appliancesonline.com.au/ak/8/f/5/6/8f56ab1cf8b3823cf9d3e3a71cb5af6dcb15da31_LG_GB_450UPLX_450L_Bottom_Mount_Fridge_Specifications_Sheet.pdf",
  "verified_at": "2026-05-09",
  "extracted": {
    "brand": "LG",
    "sku": "GB-450UPLX",
    "category": "FRIDGE",
    "dimensions": {
      "height_mm": 1724,
      "width_mm": 700,
      "depth_mm": 684,
      "door_open_90_depth_mm": null
    },
    "clearance_requirements": {
      "top_mm": 0,
      "left_mm": 0,
      "right_mm": 0,
      "rear_mm": 0
    },
    "flags": {
      "requires_plumbing": false,
      "ventilation_required": true,
      "reversible_door": null
    },
    "metadata": {
      "source_pdf_url": "https://www.appliancesonline.com.au/ak/8/f/5/6/8f56ab1cf8b3823cf9d3e3a71cb5af6dcb15da31_LG_GB_450UPLX_450L_Bottom_Mount_Fridge_Specifications_Sheet.pdf",
      "extraction_date": "2026-05-09T09:34:55.153Z",
      "confidence_score": 0.9
    }
  }
}
