[
  {
    "slug": "sydney-dishwasher",
    "city": "Sydney",
    "citySlug": "sydney",
    "state": "New South Wales",
    "stateCode": "NSW",
    "category": "dishwasher",
    "cat": "dishwasher",
    "categoryLabel": "Dishwasher",
    "models": 354,
    "url": "/location/sydney/dishwasher",
    "links": 24
  },
  {
    "slug": "sydney-fridge",
    "city": "Sydney",
    "citySlug": "sydney",
    "state": "New South Wales",
    "stateCode": "NSW",
    "category": "fridge",
    "cat": "fridge",
    "categoryLabel": "Fridge",
    "models": 1319,
    "url": "/location/sydney/fridge",
    "links": 24
  },
  {
    "slug": "sydney-washing-machine",
    "city": "Sydney",
    "citySlug": "sydney",
    "state": "New South Wales",
    "stateCode": "NSW",
    "category": "washing-machine",
    "cat": "washing_machine",
    "categoryLabel": "Washing Machine",
    "models": 424,
    "url": "/location/sydney/washing-machine",
    "links": 24
  },
  {
    "slug": "sydney-dryer",
    "city": "Sydney",
    "citySlug": "sydney",
    "state": "New South Wales",
    "stateCode": "NSW",
    "category": "dryer",
    "cat": "dryer",
    "categoryLabel": "Dryer",
    "models": 73,
    "url": "/location/sydney/dryer",
    "links": 24
  },
  {
    "slug": "sydney-oven",
    "city": "Sydney",
    "citySlug": "sydney",
    "state": "New South Wales",
    "stateCode": "NSW",
    "category": "oven",
    "cat": null,
    "categoryLabel": "Oven",
    "models": 0,
    "url": "/location/sydney/oven",
    "links": 24
  },
  {
    "slug": "melbourne-dishwasher",
    "city": "Melbourne",
    "citySlug": "melbourne",
    "state": "Victoria",
    "stateCode": "VIC",
    "category": "dishwasher",
    "cat": "dishwasher",
    "categoryLabel": "Dishwasher",
    "models": 354,
    "url": "/location/melbourne/dishwasher",
    "links": 24
  },
  {
    "slug": "melbourne-fridge",
    "city": "Melbourne",
    "citySlug": "melbourne",
    "state": "Victoria",
    "stateCode": "VIC",
    "category": "fridge",
    "cat": "fridge",
    "categoryLabel": "Fridge",
    "models": 1319,
    "url": "/location/melbourne/fridge",
    "links": 24
  },
  {
    "slug": "melbourne-washing-machine",
    "city": "Melbourne",
    "citySlug": "melbourne",
    "state": "Victoria",
    "stateCode": "VIC",
    "category": "washing-machine",
    "cat": "washing_machine",
    "categoryLabel": "Washing Machine",
    "models": 424,
    "url": "/location/melbourne/washing-machine",
    "links": 24
  },
  {
    "slug": "melbourne-dryer",
    "city": "Melbourne",
    "citySlug": "melbourne",
    "state": "Victoria",
    "stateCode": "VIC",
    "category": "dryer",
    "cat": "dryer",
    "categoryLabel": "Dryer",
    "models": 73,
    "url": "/location/melbourne/dryer",
    "links": 24
  },
  {
    "slug": "melbourne-oven",
    "city": "Melbourne",
    "citySlug": "melbourne",
    "state": "Victoria",
    "stateCode": "VIC",
    "category": "oven",
    "cat": null,
    "categoryLabel": "Oven",
    "models": 0,
    "url": "/location/melbourne/oven",
    "links": 24
  },
  {
    "slug": "brisbane-dishwasher",
    "city": "Brisbane",
    "citySlug": "brisbane",
    "state": "Queensland",
    "stateCode": "QLD",
    "category": "dishwasher",
    "cat": "dishwasher",
    "categoryLabel": "Dishwasher",
    "models": 354,
    "url": "/location/brisbane/dishwasher",
    "links": 24
  },
  {
    "slug": "brisbane-fridge",
    "city": "Brisbane",
    "citySlug": "brisbane",
    "state": "Queensland",
    "stateCode": "QLD",
    "category": "fridge",
    "cat": "fridge",
    "categoryLabel": "Fridge",
    "models": 1319,
    "url": "/location/brisbane/fridge",
    "links": 24
  },
  {
    "slug": "brisbane-washing-machine",
    "city": "Brisbane",
    "citySlug": "brisbane",
    "state": "Queensland",
    "stateCode": "QLD",
    "category": "washing-machine",
    "cat": "washing_machine",
    "categoryLabel": "Washing Machine",
    "models": 424,
    "url": "/location/brisbane/washing-machine",
    "links": 24
  },
  {
    "slug": "brisbane-dryer",
    "city": "Brisbane",
    "citySlug": "brisbane",
    "state": "Queensland",
    "stateCode": "QLD",
    "category": "dryer",
    "cat": "dryer",
    "categoryLabel": "Dryer",
    "models": 73,
    "url": "/location/brisbane/dryer",
    "links": 24
  },
  {
    "slug": "brisbane-oven",
    "city": "Brisbane",
    "citySlug": "brisbane",
    "state": "Queensland",
    "stateCode": "QLD",
    "category": "oven",
    "cat": null,
    "categoryLabel": "Oven",
    "models": 0,
    "url": "/location/brisbane/oven",
    "links": 24
  },
  {
    "slug": "perth-dishwasher",
    "city": "Perth",
    "citySlug": "perth",
    "state": "Western Australia",
    "stateCode": "WA",
    "category": "dishwasher",
    "cat": "dishwasher",
    "categoryLabel": "Dishwasher",
    "models": 354,
    "url": "/location/perth/dishwasher",
    "links": 24
  },
  {
    "slug": "perth-fridge",
    "city": "Perth",
    "citySlug": "perth",
    "state": "Western Australia",
    "stateCode": "WA",
    "category": "fridge",
    "cat": "fridge",
    "categoryLabel": "Fridge",
    "models": 1319,
    "url": "/location/perth/fridge",
    "links": 24
  },
  {
    "slug": "perth-washing-machine",
    "city": "Perth",
    "citySlug": "perth",
    "state": "Western Australia",
    "stateCode": "WA",
    "category": "washing-machine",
    "cat": "washing_machine",
    "categoryLabel": "Washing Machine",
    "models": 424,
    "url": "/location/perth/washing-machine",
    "links": 24
  },
  {
    "slug": "perth-dryer",
    "city": "Perth",
    "citySlug": "perth",
    "state": "Western Australia",
    "stateCode": "WA",
    "category": "dryer",
    "cat": "dryer",
    "categoryLabel": "Dryer",
    "models": 73,
    "url": "/location/perth/dryer",
    "links": 24
  },
  {
    "slug": "perth-oven",
    "city": "Perth",
    "citySlug": "perth",
    "state": "Western Australia",
    "stateCode": "WA",
    "category": "oven",
    "cat": null,
    "categoryLabel": "Oven",
    "models": 0,
    "url": "/location/perth/oven",
    "links": 24
  },
  {
    "slug": "adelaide-dishwasher",
    "city": "Adelaide",
    "citySlug": "adelaide",
    "state": "South Australia",
    "stateCode": "SA",
    "category": "dishwasher",
    "cat": "dishwasher",
    "categoryLabel": "Dishwasher",
    "models": 354,
    "url": "/location/adelaide/dishwasher",
    "links": 24
  },
  {
    "slug": "adelaide-fridge",
    "city": "Adelaide",
    "citySlug": "adelaide",
    "state": "South Australia",
    "stateCode": "SA",
    "category": "fridge",
    "cat": "fridge",
    "categoryLabel": "Fridge",
    "models": 1319,
    "url": "/location/adelaide/fridge",
    "links": 24
  },
  {
    "slug": "adelaide-washing-machine",
    "city": "Adelaide",
    "citySlug": "adelaide",
    "state": "South Australia",
    "stateCode": "SA",
    "category": "washing-machine",
    "cat": "washing_machine",
    "categoryLabel": "Washing Machine",
    "models": 424,
    "url": "/location/adelaide/washing-machine",
    "links": 24
  },
  {
    "slug": "adelaide-dryer",
    "city": "Adelaide",
    "citySlug": "adelaide",
    "state": "South Australia",
    "stateCode": "SA",
    "category": "dryer",
    "cat": "dryer",
    "categoryLabel": "Dryer",
    "models": 73,
    "url": "/location/adelaide/dryer",
    "links": 24
  },
  {
    "slug": "adelaide-oven",
    "city": "Adelaide",
    "citySlug": "adelaide",
    "state": "South Australia",
    "stateCode": "SA",
    "category": "oven",
    "cat": null,
    "categoryLabel": "Oven",
    "models": 0,
    "url": "/location/adelaide/oven",
    "links": 24
  },
  {
    "slug": "canberra-dishwasher",
    "city": "Canberra",
    "citySlug": "canberra",
    "state": "Australian Capital Territory",
    "stateCode": "ACT",
    "category": "dishwasher",
    "cat": "dishwasher",
    "categoryLabel": "Dishwasher",
    "models": 354,
    "url": "/location/canberra/dishwasher",
    "links": 24
  },
  {
    "slug": "canberra-fridge",
    "city": "Canberra",
    "citySlug": "canberra",
    "state": "Australian Capital Territory",
    "stateCode": "ACT",
    "category": "fridge",
    "cat": "fridge",
    "categoryLabel": "Fridge",
    "models": 1319,
    "url": "/location/canberra/fridge",
    "links": 24
  },
  {
    "slug": "canberra-washing-machine",
    "city": "Canberra",
    "citySlug": "canberra",
    "state": "Australian Capital Territory",
    "stateCode": "ACT",
    "category": "washing-machine",
    "cat": "washing_machine",
    "categoryLabel": "Washing Machine",
    "models": 424,
    "url": "/location/canberra/washing-machine",
    "links": 24
  },
  {
    "slug": "canberra-dryer",
    "city": "Canberra",
    "citySlug": "canberra",
    "state": "Australian Capital Territory",
    "stateCode": "ACT",
    "category": "dryer",
    "cat": "dryer",
    "categoryLabel": "Dryer",
    "models": 73,
    "url": "/location/canberra/dryer",
    "links": 24
  },
  {
    "slug": "canberra-oven",
    "city": "Canberra",
    "citySlug": "canberra",
    "state": "Australian Capital Territory",
    "stateCode": "ACT",
    "category": "oven",
    "cat": null,
    "categoryLabel": "Oven",
    "models": 0,
    "url": "/location/canberra/oven",
    "links": 24
  },
  {
    "slug": "hobart-dishwasher",
    "city": "Hobart",
    "citySlug": "hobart",
    "state": "Tasmania",
    "stateCode": "TAS",
    "category": "dishwasher",
    "cat": "dishwasher",
    "categoryLabel": "Dishwasher",
    "models": 354,
    "url": "/location/hobart/dishwasher",
    "links": 24
  },
  {
    "slug": "hobart-fridge",
    "city": "Hobart",
    "citySlug": "hobart",
    "state": "Tasmania",
    "stateCode": "TAS",
    "category": "fridge",
    "cat": "fridge",
    "categoryLabel": "Fridge",
    "models": 1319,
    "url": "/location/hobart/fridge",
    "links": 24
  },
  {
    "slug": "hobart-washing-machine",
    "city": "Hobart",
    "citySlug": "hobart",
    "state": "Tasmania",
    "stateCode": "TAS",
    "category": "washing-machine",
    "cat": "washing_machine",
    "categoryLabel": "Washing Machine",
    "models": 424,
    "url": "/location/hobart/washing-machine",
    "links": 24
  },
  {
    "slug": "hobart-dryer",
    "city": "Hobart",
    "citySlug": "hobart",
    "state": "Tasmania",
    "stateCode": "TAS",
    "category": "dryer",
    "cat": "dryer",
    "categoryLabel": "Dryer",
    "models": 73,
    "url": "/location/hobart/dryer",
    "links": 24
  },
  {
    "slug": "hobart-oven",
    "city": "Hobart",
    "citySlug": "hobart",
    "state": "Tasmania",
    "stateCode": "TAS",
    "category": "oven",
    "cat": null,
    "categoryLabel": "Oven",
    "models": 0,
    "url": "/location/hobart/oven",
    "links": 24
  },
  {
    "slug": "darwin-dishwasher",
    "city": "Darwin",
    "citySlug": "darwin",
    "state": "Northern Territory",
    "stateCode": "NT",
    "category": "dishwasher",
    "cat": "dishwasher",
    "categoryLabel": "Dishwasher",
    "models": 354,
    "url": "/location/darwin/dishwasher",
    "links": 24
  },
  {
    "slug": "darwin-fridge",
    "city": "Darwin",
    "citySlug": "darwin",
    "state": "Northern Territory",
    "stateCode": "NT",
    "category": "fridge",
    "cat": "fridge",
    "categoryLabel": "Fridge",
    "models": 1319,
    "url": "/location/darwin/fridge",
    "links": 24
  },
  {
    "slug": "darwin-washing-machine",
    "city": "Darwin",
    "citySlug": "darwin",
    "state": "Northern Territory",
    "stateCode": "NT",
    "category": "washing-machine",
    "cat": "washing_machine",
    "categoryLabel": "Washing Machine",
    "models": 424,
    "url": "/location/darwin/washing-machine",
    "links": 24
  },
  {
    "slug": "darwin-dryer",
    "city": "Darwin",
    "citySlug": "darwin",
    "state": "Northern Territory",
    "stateCode": "NT",
    "category": "dryer",
    "cat": "dryer",
    "categoryLabel": "Dryer",
    "models": 73,
    "url": "/location/darwin/dryer",
    "links": 24
  },
  {
    "slug": "darwin-oven",
    "city": "Darwin",
    "citySlug": "darwin",
    "state": "Northern Territory",
    "stateCode": "NT",
    "category": "oven",
    "cat": null,
    "categoryLabel": "Oven",
    "models": 0,
    "url": "/location/darwin/oven",
    "links": 24
  }
]
